s3_cli/__init__.py
s3_cli/main.py
s3_cli-0.3.0.dist-info/METADATA
s3_cli-0.3.0.dist-info/WHEEL
s3_cli-0.3.0.dist-info/RECORD
