Metadata-Version: 2.1
Name: s3-cli
Version: 0.3.0
Summary: 
Author: Diogo Neto
Author-email: diogo.neto@promptlyhealth.com
Requires-Python: >=3.9,<4.0
Classifier: Programming Language :: Python :: 3
Classifier: Programming Language :: Python :: 3.9
Classifier: Programming Language :: Python :: 3.10
Classifier: Programming Language :: Python :: 3.11
Requires-Dist: XlsxWriter (>=3.0.5,<4.0.0)
Requires-Dist: boto3 (>=1.24.18,<2.0.0)
Requires-Dist: openpyxl (>=3.0.10,<4.0.0)
